JustTry/__init__.py
JustTry/calculator.py
JustTry-0.0.7.dist-info/METADATA
JustTry-0.0.7.dist-info/WHEEL
JustTry-0.0.7.dist-info/license.txt
JustTry-0.0.7.dist-info/top_level.txt
JustTry-0.0.7.dist-info/RECORD
