Metadata-Version: 2.1
Name: JustTry
Version: 0.0.7
Summary: This is very basic
Author: Vishali
Author-email: vishali.nagathevan@gmail.com
Keywords: python,first package
Classifier: Development Status :: 3 - Alpha
Classifier: Intended Audience :: Education
Classifier: Programming Language :: Python :: 2
Classifier: Programming Language :: Python :: 3
Classifier: Operating System :: MacOS :: MacOS X
Classifier: Operating System :: Microsoft :: Windows
License-File: license.txt
